ybox/__init__.py
ybox/cmd.py
ybox/config.py
ybox/env.py
ybox/filelock.py
ybox/print.py
ybox/state.py
ybox/util.py
ybox/conf/completions/ybox.fish
ybox/conf/distros/supported.list
ybox/conf/distros/arch/add-gpg-key.sh
ybox/conf/distros/arch/distro.ini
ybox/conf/distros/arch/init-base.sh
ybox/conf/distros/arch/init-user.sh
ybox/conf/distros/arch/init.sh
ybox/conf/distros/arch/list_fmt_long.py
ybox/conf/distros/arch/pkgdeps.py
ybox/conf/distros/deb-generic/check-package.sh
ybox/conf/distros/deb-generic/distro.ini
ybox/conf/distros/deb-generic/fetch-gpg-key-id.sh
ybox/conf/distros/deb-generic/init-base.sh
ybox/conf/distros/deb-generic/init-user.sh
ybox/conf/distros/deb-generic/init.sh
ybox/conf/distros/deb-generic/list_fmt_long.py
ybox/conf/distros/deb-generic/pkgdeps.py
ybox/conf/distros/deb-oldstable/distro.ini
ybox/conf/distros/deb-stable/distro.ini
ybox/conf/distros/ubuntu2204/distro.ini
ybox/conf/distros/ubuntu2404/distro.ini
ybox/conf/profiles/apps.ini
ybox/conf/profiles/basic.ini
ybox/conf/profiles/dev.ini
ybox/conf/profiles/games.ini
ybox/conf/resources/entrypoint-base.sh
ybox/conf/resources/entrypoint-common.sh
ybox/conf/resources/entrypoint-cp.sh
ybox/conf/resources/entrypoint-root.sh
ybox/conf/resources/entrypoint-user.sh
ybox/conf/resources/entrypoint.sh
ybox/conf/resources/prime-run
ybox/conf/resources/run-in-dir
ybox/conf/resources/run-user-bash-cmd
ybox/conf/resources/ybox-systemd.template
ybox/migrate/0.9.0-0.9.10:0.9.11.py
ybox/pkg/__init__.py
ybox/pkg/clean.py
ybox/pkg/info.py
ybox/pkg/inst.py
ybox/pkg/list.py
ybox/pkg/mark.py
ybox/pkg/repair.py
ybox/pkg/repo.py
ybox/pkg/search.py
ybox/pkg/uninst.py
ybox/pkg/update.py
ybox/run/__init__.py
ybox/run/cmd.py
ybox/run/control.py
ybox/run/create.py
ybox/run/destroy.py
ybox/run/graphics.py
ybox/run/logs.py
ybox/run/ls.py
ybox/run/pkg.py
ybox/schema/0.9.1-added.sql
ybox/schema/0.9.6-added.sql
ybox/schema/init.sql
ybox/schema/migrate/0.9.0:0.9.1.sql
ybox/schema/migrate/0.9.1:0.9.2.sql
ybox-0.9.13.dist-info/licenses/LICENSE
ybox-0.9.13.dist-info/METADATA
ybox-0.9.13.dist-info/WHEEL
ybox-0.9.13.dist-info/entry_points.txt
ybox-0.9.13.dist-info/top_level.txt
ybox-0.9.13.dist-info/RECORD
