Metadata-Version: 2.4
Name: ybox
Version: 0.9.13
Summary: Securely run Linux distribution inside a container
Author-email: Sumedh Wale <sumwale@yahoo.com>, Vishal Rao <vishalrao@gmail.com>
License: Copyright (c) 2024-2025 Sumedh Wale and contributors
Project-URL: Homepage, https://github.com/sumwale/ybox
Project-URL: Issues, https://github.com/sumwale/ybox/issues
Keywords: Linux in container,toolbox,distrobox
Classifier: Development Status :: 4 - Beta
Classifier: Intended Audience :: End Users/Desktop
Classifier: License :: OSI Approved :: MIT License
Classifier: Operating System :: OS Independent
Classifier: Programming Language :: Python :: 3
Classifier: Programming Language :: Python :: 3.9
Classifier: Programming Language :: Python :: 3.10
Classifier: Programming Language :: Python :: 3.11
Classifier: Programming Language :: Python :: 3.12
Classifier: Programming Language :: Python :: 3.13
Requires-Python: >=3.9
License-File: LICENSE
Requires-Dist: packaging
Requires-Dist: simple-term-menu
Requires-Dist: tabulate>=0.9.0
Dynamic: license-file
